{"meta": {"run_id": 1044495, "rev_id": 1076872, "query_id": 99486}, "headers": ["year", "category_name", "country", "uploads", "uploaders", "images_used", "new_uploaders"], "rows": [[2019, "Images_from_Wiki_Loves_Love_2019", "Global", 6548, 1493, 6548, 0], [2019, "Wiki_Loves_Love_2019", "Global", 447, 47, 447, 0], [2019, "Wiki_Loves_Love_Workshop_Karnal_2019", "Global", 178, 32, 178, 0], [2018, "Wiki_Loves_Love_meetup_at_Wikimania_2018", "Global", 8, 4, 8, 0], [2018, "Wiki_Loves_Love_2018", "Global", 2, 1, 2, 0], [2016, "Wiki_Loves_Love_2016", "Global", 6, 5, 6, 0]]}